logsense/__init__.py
logsense/handler.py
logsense/metrics.py
logsense/sender.py
logsense_logger-0.2.0.dist-info/METADATA
logsense_logger-0.2.0.dist-info/WHEEL
logsense_logger-0.2.0.dist-info/top_level.txt
logsense_logger-0.2.0.dist-info/RECORD
