Metadata-Version: 2.1
Name: logsense-logger
Version: 0.2.0
Summary: A Python logging handler for sending logs to LogSense
Home-page: https://github.com/collectivesense/logsense-logger-python
License: Apache License, Version 2.0
Download-URL: http://pypi.python.org/pypi/logsense-logger/
Platform: UNKNOWN
Classifier: Programming Language :: Python :: 2
Classifier: Programming Language :: Python :: 2.7
Classifier: Programming Language :: Python :: 3
Classifier: Programming Language :: Python :: 3.4
Classifier: Programming Language :: Python :: 3.5
Classifier: Programming Language :: Python :: 3.6
Classifier: Programming Language :: Python :: 3.7
Classifier: Programming Language :: Python :: Implementation :: CPython
Classifier: Programming Language :: Python :: Implementation :: PyPy
Classifier: Development Status :: 5 - Production/Stable
Classifier: Topic :: System :: Logging
Classifier: Intended Audience :: Developers
Requires-Python: >=2.7,!=3.0,!=3.1,!=3.2,!=3.3,<3.8
Requires-Dist: msgpack
Requires-Dist: mona-fluent-logger
